mcp_code_scanner/__init__.py
mcp_code_scanner/cli/__init__.py
mcp_code_scanner/cli/main.py
mcp_code_scanner/compliance/__init__.py
mcp_code_scanner/compliance/owasp_mapper.py
mcp_code_scanner/config/enhanced_config.py
mcp_code_scanner/core/__init__.py
mcp_code_scanner/core/config.py
mcp_code_scanner/core/models.py
mcp_code_scanner/core/reports.py
mcp_code_scanner/core/scanner.py
mcp_code_scanner/core/tools.py
mcp_code_scanner/mcp/__init__.py
mcp_code_scanner/mcp/schemas.py
mcp_code_scanner/mcp/server.py
mcp_code_scanner/parsers/__init__.py
mcp_code_scanner/parsers/base_parser.py
mcp_code_scanner/parsers/enhanced_parsers.py
mcp_code_scanner/parsers/fastapi_parser.py
mcp_code_scanner/plugins/__init__.py
mcp_code_scanner/plugins/base_plugin.py
mcp_code_scanner/plugins/plugin_manager.py
mcp_code_scanner/reports/__init__.py
mcp_code_scanner/reports/cicd_generator.py
mcp_code_scanner/reports/enterprise_reports.py
mcp_code_scanner/reports/sarif_generator.py
mcp_code_scanner/scanners/__init__.py
mcp_code_scanner/scanners/ai_security_scanner.py
mcp_code_scanner/scanners/fastapi_scanner.py
mcp_code_scanner/utils/__init__.py
mcp_code_scanner/utils/backup_manager.py
mcp_code_scanner/utils/file_utils.py
mcp_code_scanner/utils/security.py
mcp_for_code_quality_security-2.0.0.dist-info/METADATA
mcp_for_code_quality_security-2.0.0.dist-info/WHEEL
mcp_for_code_quality_security-2.0.0.dist-info/entry_points.txt
mcp_for_code_quality_security-2.0.0.dist-info/licenses/LICENSE
mcp_for_code_quality_security-2.0.0.dist-info/RECORD
