Metadata-Version: 2.4
Name: mcp-for-code-quality-security
Version: 2.0.0
Summary: Enterprise-grade Python security analysis via Model Context Protocol (MCP)
Project-URL: Homepage, https://github.com/lgtkgtv/lgtkgtv-code_quality_security_tools_v4_mcp_agent
Project-URL: Repository, https://github.com/lgtkgtv/lgtkgtv-code_quality_security_tools_v4_mcp_agent
Project-URL: Issues, https://github.com/lgtkgtv/lgtkgtv-code_quality_security_tools_v4_mcp_agent/issues
Project-URL: Documentation, https://github.com/lgtkgtv/lgtkgtv-code_quality_security_tools_v4_mcp_agent#readme
Author-email: MCP Security Scanner Contributors <security@mcp-scanner.dev>
License: MIT License
License-File: LICENSE
Keywords: ai,analysis,claude-code,enterprise,fastapi,llm,mcp,owasp,scanner,security,vulnerability
Classifier: Development Status :: 5 - Production/Stable
Classifier: Environment :: Console
Classifier: Framework :: FastAPI
Classifier: Intended Audience :: Developers
Classifier: Intended Audience :: Information Technology
Classifier: License :: OSI Approved :: MIT License
Classifier: Operating System :: OS Independent
Classifier: Programming Language :: Python :: 3
Classifier: Programming Language :: Python :: 3.12
Classifier: Programming Language :: Python :: 3.13
Classifier: Topic :: Scientific/Engineering :: Artificial Intelligence
Classifier: Topic :: Security
Classifier: Topic :: Software Development :: Quality Assurance
Classifier: Topic :: Software Development :: Testing
Requires-Python: >=3.12
Requires-Dist: aiofiles>=23.2.1
Requires-Dist: bandit>=1.7.5
Requires-Dist: black>=23.0.0
Requires-Dist: click>=8.1.7
Requires-Dist: coverage>=7.3.0
Requires-Dist: httpx>=0.25.0
Requires-Dist: isort>=5.12.0
Requires-Dist: mcp[cli]>=1.4.0
Requires-Dist: mypy>=1.8.0
Requires-Dist: pydantic>=2.5.0
Requires-Dist: pylint>=3.0.0
Requires-Dist: pytest>=7.4.0
Requires-Dist: pyyaml>=6.0.1
Requires-Dist: rich>=13.7.0
Requires-Dist: ruff>=0.6.0
Requires-Dist: safety<3.0.0,>=2.3.0
Provides-Extra: dev
Requires-Dist: pre-commit>=3.6.0; extra == 'dev'
Requires-Dist: pytest-asyncio>=0.21.0; extra == 'dev'
Requires-Dist: pytest-cov>=4.1.0; extra == 'dev'
Requires-Dist: pytest-mock>=3.11.1; extra == 'dev'
Requires-Dist: tox>=4.11.0; extra == 'dev'
